Workbook

Sheet Hướng dẫn
A1: BỘ TEST CASE TOÀN HỆ THỐNG TECHSTORE
A2: Phiên bản | B2: Nhánh develop · lập ngày 17/10/2026
A3: Số test case | B3: 186 ca, chia theo 10 phân hệ + hạ tầng, bảo mật, phi chức năng và luồng xuyên suốt.
A4: Nguồn | B4: docs/test/HUONG_DAN_TEST_THU_CONG.md, bổ sung ca ngoại lệ, bảo mật và phi chức năng theo code nhánh develop.
A6: Cách dùng
A7: 1. Chuẩn bị | B7: Khởi động hệ thống và đặt mật khẩu tài khoản test (xem bên dưới). Chạy nhóm SYS trước; nếu SYS lỗi thì các nhóm khác sẽ bị chặn.
A8: 2. Thực hiện | B8: Ở sheet 'Test case', làm theo cột 'Các bước thực hiện', so với 'Kết quả mong đợi' và 'Cách kiểm chứng'.
A9: 3. Ghi kết quả | B9: Chỉ điền vào 5 cột có tiêu đề màu vàng đậm (nền ô vàng nhạt): Kết quả thực tế, Trạng thái, Người test, Ngày test, Mã lỗi / Ghi chú.
A10: 4. Ghi lỗi | B10: Ca 'Không đạt' thì thêm một dòng ở sheet 'Ghi lỗi' và ghi mã lỗi đó vào cột 'Mã lỗi / Ghi chú'. Dòng xám đầu tiên của sheet 'Ghi lỗi' là ví dụ, xóa khi dùng.
A11: 5. Theo dõi | B11: Sheet 'Tổng hợp' tự đếm theo phân hệ và mức ưu tiên. Lọc cột Trạng thái hoặc Ưu tiên bằng bộ lọc ở dòng tiêu đề.
A12: Trước khi báo lỗi | B12: Xem sheet 'Hành vi đã biết': các hành vi ở đó là hiện trạng đã ghi nhận, không phải lỗi mới.
A14: Giá trị cột Trạng thái
A15: Chưa test | B15: Mặc định.
A16: Đạt | B16: Kết quả thực tế khớp kết quả mong đợi.
A17: Không đạt | B17: Có sai khác. Ghi lỗi ở sheet 'Ghi lỗi'.
A18: Bị chặn | B18: Không thực hiện được vì điều kiện chưa có (service chưa chạy, ca trước lỗi, thiếu dữ liệu).
A19: Bỏ qua | B19: Không áp dụng cho đợt test này (ví dụ chưa có Google Client ID).
A21: Địa chỉ
A22: Web (FE) | B22: http://localhost:5173
A23: API Gateway | B23: http://localhost:8080
A24: Eureka | B24: http://localhost:8761
A25: Keycloak | B25: http://localhost:8083 (Admin Console: realm master)
A26: Debezium Connect | B26: http://localhost:8088
A27: MinIO Console | B27: http://localhost:9001
A28: Elasticsearch | B28: http://localhost:9200
A29: MariaDB | B29: localhost:3308 (user/mật khẩu trong BE/.env)
A30: Swagger AI | B30: Search 8001/docs · Chatbot 8002/docs · Recs 8003/docs · Forecast 8004/docs
A32: Tài khoản test (realm ecommerce-realm)
A33: admin (ROLE_ADMIN) | B33: admin@gmail.com · mật khẩu 12345678 (đặt lại ngày 17/10/2026).
A34: staff (ROLE_STAFF) | B34: staff@gmail.com · chưa biết mật khẩu, đặt lại theo HUONG_DAN_TEST_THU_CONG.md §2.
A35: customer (ROLE_CUSTOMER) | B35: customer@gmail.com · chưa có mật khẩu, đặt lại theo HUONG_DAN_TEST_THU_CONG.md §2.
A36: Lưu ý email | B36: Các địa chỉ *@gmail.com trên là của người khác. Trước khi test email (PH7), đổi email tài khoản test sang email của bạn.
A38: Hiện trạng môi trường (17/10/2026)
A39: Đang chạy | B39: Hạ tầng Docker, 8 service Java, Gateway, AI search (8001), FE. Đã nạp 1.123 sản phẩm, tồn kho 10/phiên bản, chỉ mục tìm kiếm.
A40: Chưa chạy | B40: chatbot (8002), recs (8003), forecast (8004). Các ca cần những service này ghi 'Bị chặn' cho đến khi bật.
A41: Chưa có dữ liệu | B41: Dữ liệu tổng hợp user/đơn/hành vi (tools/data-seed). Nhóm PH9 cần dữ liệu này.
A43: Quy tắc an toàn
A44: Kafka | B44: Không gửi message tay vào các topic dùng chung (order-events, payment-events…). Chỉ tạo dữ liệu qua giao diện/API; các lệnh Kafka trong file này chỉ đọc.
A45: Docker | B45: Không dùng `docker compose down -v` (xóa toàn bộ dữ liệu).
A46: Dọn dữ liệu | B46: Sau khi test: hủy đơn test chưa giao, nhập lại kho, tắt/xóa chiến dịch test, xóa tài khoản test tự đăng ký.
A47: Công thức | B47: Sheet 'Tổng hợp' dùng công thức; Excel tự tính khi mở file.

Sheet Test case
A1: ID | B1: Phân hệ | C1: Chức năng | D1: Tiêu đề test case | E1: Loại | F1: Ưu tiên | G1: Tài khoản | H1: Tiền điều kiện | I1: Các bước thực hiện | J1: Dữ liệu test | K1: Kết quả mong đợi | L1: Cách kiểm chứng | M1: Kết quả thực tế | N1: Trạng thái | O1: Người test | P1: Ngày test | Q1: Mã lỗi / Ghi chú
A2: SYS-01 | B2: SYS – Hạ tầng & khởi động | C2: Docker | D2: Các container hạ tầng đang chạy | E2: Chức năng | F2: Cao | G2: — | H2: Docker Desktop đang chạy. | I2: 1. Chạy `docker ps -a`. | K2: infra-mariadb, mongodb, redis, kafka, debezium-connect, elasticsearch, minio, keycloak, eureka, gateway đều Up. `infra-debezium-init` Exited (0) là bình thường. | L2: Cột STATUS của `docker ps -a`. | N2: Chưa test
A3: SYS-02 | B3: SYS – Hạ tầng & khởi động | C3: Eureka | D3: Đủ 9 service đăng ký Eureka | E3: Chức năng | F3: Cao | G3: — | H3: Đã chạy 8 service Java. | I3: 1. Mở http://localhost:8761. | K3: API-GATEWAY, USER, PRODUCT, ORDER, INVENTORY, PAYMENT, PROMOTION, NOTIFICATION, CHAT-SERVICE đều UP. | L3: Bảng 'Instances currently registered'. | N3: Chưa test
A4: SYS-03 | B4: SYS – Hạ tầng & khởi động | C4: Gateway | D4: Gateway định tuyến tới product-service | E4: Tích hợp | F4: Cao | G4: — | H4: SYS-02 đạt. | I4: 1. Mở http://localhost:8080/api/v1/public/products?page=0&size=1. | K4: HTTP 200, `code` = SUCCESS, có 1 sản phẩm. | L4: Nội dung JSON trả về. | N4: Chưa test
A5: SYS-04 | B5: SYS – Hạ tầng & khởi động | C5: Debezium | D5: Hai connector outbox đang chạy | E5: Tích hợp | F5: Cao | G5: — | H5: Order/payment-service đã khởi động ít nhất 1 lần. | I5: 1. Mở http://localhost:8088/connectors/order-outbox-connector/status. 2. Mở .../payment-outbox-connector/status. | K5: Cả connector và task đều RUNNING. | L5: Trường `connector.state`, `tasks[].state`. | N5: Chưa test
A6: SYS-05 | B6: SYS – Hạ tầng & khởi động | C6: Keycloak | D6: Realm ecommerce-realm sẵn sàng | E6: Chức năng | F6: Cao | G6: — | I6: 1. Mở http://localhost:8083/realms/ecommerce-realm. | K6: HTTP 200, có `public_key`. | L6: JSON trả về. | N6: Chưa test
A7: SYS-06 | B7: SYS – Hạ tầng & khởi động | C7: AI | D7: Health của các service AI | E7: Chức năng | F7: Trung bình | G7: — | H7: Đã bật service AI tương ứng (8002/8003/8004). | I7: 1. Mở lần lượt http://localhost:8001/health, 8002/health, 8003/health, 8004/health. | K7: Mỗi service trả HTTP 200, `status` = UP. | L7: JSON trả về. | N7: Chưa test
A8: SYS-07 | B8: SYS – Hạ tầng & khởi động | C8: Frontend | D8: FE tải được trang chủ | E8: Chức năng | F8: Cao | G8: Khách (chưa đăng nhập) | H8: `npm run dev` trong FE. | I8: 1. Mở http://localhost:5173. 2. Mở F12 → Console. | K8: Trang chủ hiển thị, Console không có lỗi đỏ. | L8: F12 → Console. | N8: Chưa test
A9: SYS-08 | B9: SYS – Hạ tầng & khởi động | C9: Elasticsearch | D9: Chỉ mục sản phẩm có dữ liệu | E9: Tích hợp | F9: Trung bình | G9: — | H9: Đã nạp catalog. | I9: 1. Mở http://localhost:9200/products/_count. | K9: `count` bằng số sản phẩm đang có (≈1.123 sau khi nạp catalog). | L9: JSON trả về. | N9: Chưa test
A10: SYS-09 | B10: SYS – Hạ tầng & khởi động | C10: MinIO | D10: MinIO có bucket ảnh | E10: Tích hợp | F10: Thấp | G10: — | I10: 1. Mở http://localhost:9001, đăng nhập bằng thông tin MinIO trong `BE/docker-compose-infra.yml`. | K10: Thấy bucket ảnh sản phẩm và bucket `chat-images` (bucket chat được tạo khi gửi ảnh đầu tiên). | L10: Giao diện MinIO. | N10: Chưa test
A11: PH1-01 | B11: PH1 – Tài khoản & phân quyền | C11: Đăng ký | D11: Đăng ký tài khoản mới | E11: Chức năng | F11: Cao | G11: Khách (chưa đăng nhập) | H11: Email chưa dùng. | I11: 1. Vào http://localhost:5173/register. 2. Điền họ tên, email, mật khẩu. 3. Gửi. | J11: Email của bạn | K11: Chuyển sang trang Keycloak (giao diện techstore), tạo xong quay về trang chủ ở trạng thái đã đăng nhập. | L11: Keycloak → ecommerce-realm → Users có user mới, role ROLE_CUSTOMER. | N11: Chưa test
A12: PH1-02 | B12: PH1 – Tài khoản & phân quyền | C12: Đăng ký | D12: Đăng ký với email đã tồn tại | E12: Ngoại lệ | F12: Trung bình | G12: Khách (chưa đăng nhập) | H12: Email đã có trong realm. | I12: 1. Đăng ký lại bằng email ở PH1-01. | K12: Keycloak báo email đã tồn tại, không tạo user mới. | L12: Keycloak → Users. | N12: Chưa test
A13: PH1-03 | B13: PH1 – Tài khoản & phân quyền | C13: Hồ sơ | D13: Tự tạo hồ sơ ở lần truy cập đầu | E13: Tích hợp | F13: Cao | G13: Tài khoản vừa đăng ký | H13: PH1-01 đạt. | I13: 1. Mở /profile lần đầu. | K13: Trang hồ sơ hiển thị, user-service tự tạo hồ sơ và phát `user-created-events`. | L13: MariaDB `ecommerce_user_db.users` có dòng mới với keycloak_user_id của tài khoản. | N13: Chưa test
A14: PH1-04 | B14: PH1 – Tài khoản & phân quyền | C14: Đăng nhập | D14: Đăng nhập đúng mật khẩu | E14: Chức năng | F14: Cao | G14: customer | H14: Đã đặt mật khẩu cho customer. | I14: 1. Vào /login. 2. Nhập username và mật khẩu. | K14: Đăng nhập thành công, header hiện tên tài khoản. | L14: Giao diện header. | N14: Chưa test
A15: PH1-05 | B15: PH1 – Tài khoản & phân quyền | C15: Đăng nhập | D15: Đăng nhập sai mật khẩu | E15: Ngoại lệ | F15: Cao | G15: customer | I15: 1. Vào /login. 2. Nhập sai mật khẩu. | J15: Mật khẩu sai bất kỳ | K15: Keycloak báo sai thông tin đăng nhập, không vào được. | L15: Giao diện Keycloak. | N15: Chưa test
A16: PH1-06 | B16: PH1 – Tài khoản & phân quyền | C16: Đăng nhập | D16: Đăng nhập bằng Google | E16: Tích hợp | F16: Thấp | G16: Khách (chưa đăng nhập) | H16: Có GOOGLE_CLIENT_ID trong BE/.env. | I16: 1. Trang đăng nhập Keycloak → bấm Google. 2. Chọn tài khoản Google. | K16: Đăng nhập thành công, quay về web. | L16: Keycloak → Users có user liên kết Google. | N16: Chưa test
A17: PH1-07 | B17: PH1 – Tài khoản & phân quyền | C17: Hồ sơ | D17: Sửa họ tên, SĐT, ảnh đại diện | E17: Chức năng | F17: Trung bình | G17: customer | I17: 1. /profile?tab=account. 2. Sửa họ tên, SĐT, tải ảnh. 3. Lưu, rồi F5. | J17: Ảnh JPG < 2MB | K17: Lưu thành công, tải lại vẫn giữ thông tin mới. | L17: Ảnh có trong MinIO. | N17: Chưa test
A18: PH1-08 | B18: PH1 – Tài khoản & phân quyền | C18: Địa chỉ | D18: Thêm, sửa, xóa địa chỉ | E18: Chức năng | F18: Cao | G18: customer | I18: 1. /profile?tab=addresses → Thêm. 2. Chọn tỉnh → phường/xã, nhập chi tiết. 3. Sửa địa chỉ vừa thêm. 4. Xóa. | K18: Thêm/sửa/xóa thành công; danh sách phường/xã đổi theo tỉnh. | L18: Danh sách địa chỉ. | N18: Chưa test
A19: PH1-09 | B19: PH1 – Tài khoản & phân quyền | C19: Địa chỉ | D19: Chỉ một địa chỉ mặc định | E19: Chức năng | F19: Trung bình | G19: customer | H19: Có ≥ 2 địa chỉ. | I19: 1. Đặt địa chỉ B làm mặc định. | K19: B là mặc định, địa chỉ mặc định cũ mất cờ mặc định. | L19: Danh sách địa chỉ. | N19: Chưa test
A20: PH1-10 | B20: PH1 – Tài khoản & phân quyền | C20: Hạng thành viên | D20: Xem hạng và điểm | E20: Chức năng | F20: Trung bình | G20: customer | I20: 1. /profile?tab=membership. | K20: Hiện hạng (MEMBER/SILVER/GOLD/VIP) và số điểm hiện có. | L20: Giao diện. | N20: Chưa test
A21: PH1-11 | B21: PH1 – Tài khoản & phân quyền | C21: Phân quyền | D21: Chưa đăng nhập vào trang cần đăng nhập | E21: Phân quyền | F21: Cao | G21: Khách (chưa đăng nhập) | H21: Đã đăng xuất. | I21: 1. Mở /cart. | K21: Bị chuyển sang đăng nhập. | L21: URL trình duyệt. | N21: Chưa test
A22: PH1-12 | B22: PH1 – Tài khoản & phân quyền | C22: Phân quyền | D22: Customer vào trang quản trị | E22: Phân quyền | F22: Cao | G22: customer | I22: 1. Mở /admin. | K22: Bị đẩy về trang chủ. | L22: URL trình duyệt. | N22: Chưa test
A23: PH1-13 | B23: PH1 – Tài khoản & phân quyền | C23: Phân quyền | D23: Staff vào trang quản trị | E23: Phân quyền | F23: Cao | G23: staff | I23: 1. Mở /admin. | K23: Vào được, thấy đủ các tab. | L23: Giao diện. | N23: Chưa test
A24: PH1-14 | B24: PH1 – Tài khoản & phân quyền | C24: Phân quyền | D24: Staff không được đổi vai trò / khóa user | E24: Phân quyền | F24: Cao | G24: staff | I24: 1. Tab Customers → đổi vai trò hoặc khóa một user. | K24: Thao tác bị từ chối (HTTP 403). | L24: F12 → Network. | N24: Chưa test
A25: PH1-15 | B25: PH1 – Tài khoản & phân quyền | C25: Quản trị khách hàng | D25: Admin đổi hạng khách hàng | E25: Chức năng | F25: Trung bình | G25: admin | I25: 1. Tab Customers → đổi hạng một user test từ MEMBER sang GOLD. 2. Đăng nhập user đó, xem tab membership. | K25: Hạng mới hiển thị đúng. | L25: Giao diện 2 phía. | N25: Chưa test
A26: PH1-16 | B26: PH1 – Tài khoản & phân quyền | C26: Quản trị khách hàng | D26: Admin khóa (blacklist) khách hàng | E26: Chức năng | F26: Trung bình | G26: admin | I26: 1. Tab Customers → khóa một user test. | K26: Trạng thái khóa được lưu và hiển thị trong danh sách. | L26: Danh sách khách; cột is_blacklisted trong DB. | N26: Chưa test
A27: PH1-17 | B27: PH1 – Tài khoản & phân quyền | C27: Quản trị khách hàng | D27: Admin đặt lại mật khẩu khách hàng | E27: Chức năng | F27: Trung bình | G27: admin | I27: 1. Tab Customers → reset mật khẩu một user test. 2. Đăng nhập bằng mật khẩu mới. | K27: Đăng nhập được bằng mật khẩu mới. | L27: Đăng nhập thử. | N27: Chưa test
A28: PH1-18 | B28: PH1 – Tài khoản & phân quyền | C28: Quản trị khách hàng | D28: Admin gán vai trò STAFF | E28: Phân quyền | F28: Trung bình | G28: admin | I28: 1. Gán vai trò STAFF cho user test. 2. User đó đăng xuất, đăng nhập lại, mở /admin. | K28: User vào được /admin. | L28: Giao diện. | N28: Chưa test
A29: PH1-19 | B29: PH1 – Tài khoản & phân quyền | C29: Phiên đăng nhập | D29: Token hết hạn khi đang dùng | E29: Ngoại lệ | F29: Thấp | G29: customer | I29: 1. Đăng nhập, để tab mở > 15 phút. 2. Thao tác một trang cần đăng nhập. | K29: FE tự làm mới token hoặc yêu cầu đăng nhập lại; không lỗi trắng trang. | L29: Giao diện, F12 → Network. | N29: Chưa test
A30: PH2-01 | B30: PH2 – Sản phẩm & tìm kiếm | C30: Trang chủ | D30: Trang chủ cho khách | E30: Chức năng | F30: Cao | G30: Khách (chưa đăng nhập) | H30: Đã nạp catalog. | I30: 1. Mở /. | K30: Có flash deal, danh mục, thương hiệu, khối gợi ý 3 tab. | L30: Giao diện. | N30: Chưa test
A31: PH2-02 | B31: PH2 – Sản phẩm & tìm kiếm | C31: Danh mục | D31: Lọc theo danh mục | E31: Chức năng | F31: Cao | G31: Khách (chưa đăng nhập) | I31: 1. /category → chọn danh mục 'Laptop'. | K31: Chỉ hiện sản phẩm thuộc danh mục đã chọn. | L31: Giao diện. | N31: Chưa test
A32: PH2-03 | B32: PH2 – Sản phẩm & tìm kiếm | C32: Danh mục | D32: Lọc theo khoảng giá | E32: Chức năng | F32: Trung bình | G32: Khách (chưa đăng nhập) | I32: 1. /category → đặt khoảng giá. | J32: 5.000.000 – 10.000.000đ | K32: Mọi sản phẩm nằm trong khoảng giá. | L32: Giao diện. | N32: Chưa test
A33: PH2-04 | B33: PH2 – Sản phẩm & tìm kiếm | C33: Danh mục | D33: Lọc theo thương hiệu | E33: Chức năng | F33: Trung bình | G33: Khách (chưa đăng nhập) | I33: 1. /category → chọn thương hiệu. | J33: Samsung | K33: Chỉ hiện sản phẩm của thương hiệu đã chọn. | L33: Giao diện. | N33: Chưa test
A34: PH2-05 | B34: PH2 – Sản phẩm & tìm kiếm | C34: Danh mục | D34: Sắp xếp theo giá | E34: Chức năng | F34: Trung bình | G34: Khách (chưa đăng nhập) | I34: 1. Đổi sắp xếp giá tăng dần, rồi giảm dần. | K34: Thứ tự đúng theo giá. | L34: Giao diện. | N34: Chưa test
A35: PH2-06 | B35: PH2 – Sản phẩm & tìm kiếm | C35: Danh mục | D35: Phân trang | E35: Chức năng | F35: Thấp | G35: Khách (chưa đăng nhập) | I35: 1. Sang trang 2, 3. | K35: Danh sách đổi, không trùng sản phẩm giữa các trang. | L35: Giao diện. | N35: Chưa test
A36: PH2-07 | B36: PH2 – Sản phẩm & tìm kiếm | C36: Chi tiết | D36: Xem chi tiết khi chưa đăng nhập | E36: Chức năng | F36: Cao | G36: Khách (chưa đăng nhập) | I36: 1. Mở /product/1. | K36: Trang hiện đủ thông tin, tên người đánh giá hiển thị. | L36: Giao diện. | N36: Chưa test
A37: PH2-08 | B37: PH2 – Sản phẩm & tìm kiếm | C37: Chi tiết | D37: Chọn phiên bản sản phẩm | E37: Chức năng | F37: Cao | G37: Khách (chưa đăng nhập) | H37: Sản phẩm có ≥ 2 phiên bản. | I37: 1. Chọn màu/dung lượng khác. | K37: Giá và tồn kho đổi theo phiên bản. | L37: Giao diện. | N37: Chưa test
A38: PH2-09 | B38: PH2 – Sản phẩm & tìm kiếm | C38: Chi tiết | D38: Ảnh và các tab thông tin | E38: Chức năng | F38: Thấp | G38: Khách (chưa đăng nhập) | I38: 1. Phóng to ảnh. 2. Mở tab thông số, bảo hành, đánh giá. | K38: Ảnh phóng to được; các tab hiển thị nội dung. | L38: Giao diện. | N38: Chưa test
A39: PH2-10 | B39: PH2 – Sản phẩm & tìm kiếm | C39: Chi tiết | D39: Thêm vào giỏ khi chưa đăng nhập | E39: Phân quyền | F39: Cao | G39: Khách (chưa đăng nhập) | I39: 1. Bấm Thêm vào giỏ. | K39: Yêu cầu đăng nhập. | L39: Giao diện. | N39: Chưa test
A40: PH2-11 | B40: PH2 – Sản phẩm & tìm kiếm | C40: Tìm kiếm | D40: Tìm theo từ khóa trên header | E40: Chức năng | F40: Cao | G40: Khách (chưa đăng nhập) | I40: 1. Gõ 'iphone' vào ô tìm kiếm, Enter. | J40: iphone | K40: Trang /search?q=iphone có kết quả là iPhone. | L40: Giao diện. | N40: Chưa test
A41: PH2-12 | B41: PH2 – Sản phẩm & tìm kiếm | C41: Tìm kiếm | D41: Tìm từ khóa tiếng Việt có dấu | E41: Chức năng | F41: Trung bình | G41: Khách (chưa đăng nhập) | I41: 1. Tìm 'tai nghe'. | J41: tai nghe | K41: Có kết quả là tai nghe. | L41: Giao diện. | N41: Chưa test
A42: PH2-13 | B42: PH2 – Sản phẩm & tìm kiếm | C42: Tìm kiếm | D42: Tìm từ khóa không tồn tại | E42: Ngoại lệ | F42: Trung bình | G42: Khách (chưa đăng nhập) | I42: 1. Tìm 'xyzabc123'. | J42: xyzabc123 | K42: Thông báo không có kết quả, không lỗi. | L42: Giao diện. | N42: Chưa test
A43: PH2-14 | B43: PH2 – Sản phẩm & tìm kiếm | C43: Tìm kiếm ảnh | D43: Tìm bằng ảnh | E43: Chức năng | F43: Cao | G43: Khách (chưa đăng nhập) | H43: Đã build chỉ mục ảnh; search-service chạy. | I43: 1. Bấm biểu tượng máy ảnh trên header. 2. Tải ảnh một chiếc điện thoại. | J43: Ảnh điện thoại JPG | K43: Chuyển /search?imageSearch=true, kết quả là sản phẩm giống ảnh. | L43: Giao diện. | N43: Chưa test
A44: PH2-15 | B44: PH2 – Sản phẩm & tìm kiếm | C44: Tìm kiếm ảnh | D44: Tìm bằng file không phải ảnh | E44: Ngoại lệ | F44: Trung bình | G44: Khách (chưa đăng nhập) | I44: 1. Tải lên file .txt hoặc .pdf ở chức năng tìm bằng ảnh. | J44: file.txt | K44: Báo lỗi định dạng; API trả 400, không treo trang. | L44: F12 → Network. | N44: Chưa test
A45: PH2-16 | B45: PH2 – Sản phẩm & tìm kiếm | C45: Tìm kiếm ngữ nghĩa | D45: Tìm kiếm lai qua Swagger | E45: Chức năng | F45: Trung bình | G45: — | H45: search-service chạy. | I45: 1. http://localhost:8001/docs → GET /api/v1/search, q = 'tai nghe chống ồn' → Execute. | J45: tai nghe chống ồn | K45: Trả danh sách sản phẩm liên quan (kết hợp BM25 + vector + RRF). | L45: JSON trả về. | N45: Chưa test
A46: PH2-17 | B46: PH2 – Sản phẩm & tìm kiếm | C46: Tìm kiếm ngữ nghĩa | D46: Gợi ý từ khóa | E46: Chức năng | F46: Thấp | G46: — | I46: 1. Swagger 8001 → GET /api/v1/search/suggest?q=ip. | J46: ip | K46: Trả danh sách gợi ý từ khóa. | L46: JSON trả về. | N46: Chưa test
A47: PH2-18 | B47: PH2 – Sản phẩm & tìm kiếm | C47: Tìm kiếm ngữ nghĩa | D47: Sản phẩm tương tự | E47: Chức năng | F47: Thấp | G47: — | H47: Đã build chỉ mục. | I47: 1. Swagger 8001 → GET /api/v1/search/similar/{product_id}. | J47: product_id = 1 | K47: Trả danh sách sản phẩm tương tự. | L47: JSON trả về. | N47: Chưa test
A48: PH2-19 | B48: PH2 – Sản phẩm & tìm kiếm | C48: Yêu thích | D48: Thêm và bỏ yêu thích | E48: Chức năng | F48: Trung bình | G48: customer | I48: 1. Bấm tim trên trang sản phẩm. 2. Mở /wishlist. 3. Bỏ tim. | K48: Sản phẩm xuất hiện rồi biến mất khỏi danh sách yêu thích. | L48: Giao diện. | N48: Chưa test
A49: PH2-20 | B49: PH2 – Sản phẩm & tìm kiếm | C49: Đánh giá | D49: Đánh giá sản phẩm đã nhận | E49: Chức năng | F49: Cao | G49: customer | H49: Có đơn DELIVERED chứa sản phẩm (PH3-09). | I49: 1. Mở sản phẩm → viết đánh giá, chọn sao. 2. Gửi. | J49: 5 sao + nội dung | K49: Gửi thành công, đánh giá hiển thị. | L49: Giao diện. | N49: Chưa test
A50: PH2-21 | B50: PH2 – Sản phẩm & tìm kiếm | C50: Đánh giá | D50: Đánh giá sản phẩm chưa mua | E50: Ngoại lệ | F50: Cao | G50: customer | H50: Chưa mua sản phẩm. | I50: 1. Thử viết đánh giá. | K50: Bị chặn, báo chỉ đánh giá sản phẩm đã mua. | L50: Giao diện / F12 → Network. | N50: Chưa test
A51: PH2-22 | B51: PH2 – Sản phẩm & tìm kiếm | C51: Đánh giá | D51: Đánh giá lần 2 cho cùng sản phẩm, cùng đơn | E51: Ngoại lệ | F51: Trung bình | G51: customer | H51: PH2-20 đạt. | I51: 1. Viết đánh giá thêm lần nữa cho cùng sản phẩm của cùng đơn. | K51: Bị chặn. | L51: Giao diện / F12 → Network. | N51: Chưa test
A52: PH2-23 | B52: PH2 – Sản phẩm & tìm kiếm | C52: Đánh giá | D52: Admin trả lời đánh giá | E52: Chức năng | F52: Thấp | G52: admin | H52: Có đánh giá. | I52: 1. Tab Reviews → trả lời. | K52: Câu trả lời hiển thị dưới đánh giá ở trang sản phẩm. | L52: Giao diện khách. | N52: Chưa test
A53: PH2-24 | B53: PH2 – Sản phẩm & tìm kiếm | C53: Quản trị danh mục | D53: Thêm danh mục con và thuộc tính | E53: Chức năng | F53: Trung bình | G53: admin | I53: 1. Tab Categories → thêm danh mục con. 2. Thêm thuộc tính. | K53: Danh mục mới hiện ở /category. | L53: Giao diện khách. | N53: Chưa test
A54: PH2-25 | B54: PH2 – Sản phẩm & tìm kiếm | C54: Quản trị thương hiệu | D54: Thêm và sửa thương hiệu | E54: Chức năng | F54: Thấp | G54: admin | I54: 1. Tab Brand → thêm, rồi sửa. | K54: Thương hiệu được lưu và hiển thị. | L54: Giao diện. | N54: Chưa test
A55: PH2-26 | B55: PH2 – Sản phẩm & tìm kiếm | C55: Quản trị sản phẩm | D55: Tạo sản phẩm 2 phiên bản kèm ảnh | E55: Chức năng | F55: Cao | G55: admin | I55: 1. Tab Add Products → nhập thông tin, 2 phiên bản, tải ảnh. 2. Lưu. 3. Tìm sản phẩm ở ô tìm kiếm khách. | K55: Lưu thành công; sản phẩm hiện ở trang khách và tìm thấy bằng ô tìm kiếm. | L55: MinIO có ảnh; ES có document mới. | N55: Chưa test
A56: PH2-27 | B56: PH2 – Sản phẩm & tìm kiếm | C56: Quản trị sản phẩm | D56: Tạo sản phẩm thiếu tên hoặc slug | E56: Ngoại lệ | F56: Trung bình | G56: admin | I56: 1. Để trống tên (hoặc slug), bấm lưu. | K56: Báo lỗi bắt buộc nhập, không lưu. | L56: Giao diện / F12 → Network (400). | N56: Chưa test
A57: PH2-28 | B57: PH2 – Sản phẩm & tìm kiếm | C57: Quản trị sản phẩm | D57: Tạo sản phẩm trùng slug | E57: Ngoại lệ | F57: Trung bình | G57: admin | I57: 1. Tạo sản phẩm với slug đã tồn tại. | K57: Báo lỗi slug đã tồn tại. | L57: Giao diện / F12 → Network. | N57: Chưa test
A58: PH2-29 | B58: PH2 – Sản phẩm & tìm kiếm | C58: Quản trị sản phẩm | D58: Sửa giá sản phẩm | E58: Chức năng | F58: Cao | G58: admin | I58: 1. Product List → sửa giá một sản phẩm. 2. Mở trang sản phẩm ở tab khách. | K58: Trang khách hiện giá mới (cache đã được xóa). | L58: Giao diện khách. | N58: Chưa test
A59: PH2-30 | B59: PH2 – Sản phẩm & tìm kiếm | C59: Quản trị sản phẩm | D59: Staff tạo, sửa được nhưng không xóa được | E59: Phân quyền | F59: Cao | G59: staff | I59: 1. Tạo và sửa một sản phẩm. 2. Tìm nút xóa. | K59: Tạo/sửa thành công; nút xóa không hiện (API xóa trả 403). | L59: Giao diện / F12 → Network. | N59: Chưa test
A60: PH2-31 | B60: PH2 – Sản phẩm & tìm kiếm | C60: Quản trị sản phẩm | D60: Admin xóa sản phẩm | E60: Chức năng | F60: Trung bình | G60: admin | H60: Sản phẩm ở PH2-26. | I60: 1. Product List → xóa sản phẩm test. | K60: Sản phẩm biến mất khỏi trang khách và kết quả tìm kiếm. | L60: Giao diện khách. | N60: Chưa test
A61: PH3-01 | B61: PH3 – Giỏ hàng & đơn hàng | C61: Giỏ hàng | D61: Thêm sản phẩm vào giỏ | E61: Chức năng | F61: Cao | G61: customer | I61: 1. Thêm 1 sản phẩm vào giỏ. 2. Mở /cart. | K61: Giỏ hiện đúng sản phẩm, giá; có khối gợi ý mua kèm. | L61: Giao diện. | N61: Chưa test
A62: PH3-02 | B62: PH3 – Giỏ hàng & đơn hàng | C62: Giỏ hàng | D62: Đổi số lượng | E62: Chức năng | F62: Cao | G62: customer | H62: Giỏ có sản phẩm. | I62: 1. Tăng/giảm số lượng. | K62: Tổng tiền cập nhật đúng. | L62: Giao diện. | N62: Chưa test
A63: PH3-03 | B63: PH3 – Giỏ hàng & đơn hàng | C63: Giỏ hàng | D63: Xóa sản phẩm khỏi giỏ | E63: Chức năng | F63: Trung bình | G63: customer | I63: 1. Xóa một dòng trong giỏ. | K63: Dòng biến mất, tổng tiền cập nhật. | L63: Giao diện. | N63: Chưa test
A64: PH3-04 | B64: PH3 – Giỏ hàng & đơn hàng | C64: Giỏ hàng | D64: Thêm số lượng vượt tồn kho | E64: Ngoại lệ | F64: Cao | G64: customer | H64: Biết tồn kho của phiên bản. | I64: 1. Đặt số lượng lớn hơn tồn kho. | J64: Tồn + 1 | K64: Báo không đủ hàng. | L64: Giao diện. | N64: Chưa test
A65: PH3-05 | B65: PH3 – Giỏ hàng & đơn hàng | C65: Checkout | D65: Tính tiền ở trang checkout | E65: Chức năng | F65: Cao | G65: customer | H65: Giỏ có sản phẩm; có địa chỉ. | I65: 1. Mở /checkout, chọn địa chỉ, chọn COD. | K65: Phí vận chuyển 30.000đ; VAT 10% tính trên (tạm tính − giảm voucher − giảm điểm); tổng tiền do server tính. | L65: Đối chiếu số trên giao diện với công thức. | N65: Chưa test
A66: PH3-06 | B66: PH3 – Giỏ hàng & đơn hàng | C66: Đặt hàng | D66: Đặt đơn COD | E66: Chức năng | F66: Cao | G66: customer | H66: PH3-05. | I66: 1. Bấm đặt hàng. | K66: Chuyển sang trang đơn; vài giây sau trạng thái 'Chờ thanh toán' rồi 'Đã xác nhận'. | L66: MariaDB `ecommerce_order_db.orders.status` = CONFIRMED. | N66: Chưa test
A67: PH3-07 | B67: PH3 – Giỏ hàng & đơn hàng | C67: Đặt hàng | D67: Tồn kho giảm sau khi đặt | E67: Tích hợp | F67: Cao | G67: admin | H67: PH3-06; đã ghi lại tồn kho trước khi đặt. | I67: 1. Admin → Quản Lý Tồn Kho → xem sản phẩm vừa mua. | K67: Tồn kho giảm đúng số lượng đã mua. | L67: Lịch sử giao dịch kho có dòng DEDUCT. | N67: Chưa test
A68: PH3-08 | B68: PH3 – Giỏ hàng & đơn hàng | C68: Vận chuyển | D68: Admin xác nhận giao hàng | E68: Chức năng | F68: Cao | G68: admin | H68: Đơn CONFIRMED. | I68: 1. Order Management → mở đơn → Xác Nhận Giao Hàng. | K68: Trạng thái SHIPPED, có mã vận đơn MOCK-GHTK-... | L68: Giao diện. | N68: Chưa test
A69: PH3-09 | B69: PH3 – Giỏ hàng & đơn hàng | C69: Vận chuyển | D69: Admin xác nhận đã giao | E69: Chức năng | F69: Cao | G69: admin | H69: Đơn SHIPPED. | I69: 1. Bấm Đã Giao Thành Công. | K69: Trạng thái DELIVERED; thanh toán COD chuyển SUCCESS. | L69: Tab Transaction. | N69: Chưa test
A70: PH3-10 | B70: PH3 – Giỏ hàng & đơn hàng | C70: Đơn hàng | D70: Khách xem danh sách và chi tiết đơn | E70: Chức năng | F70: Trung bình | G70: customer | I70: 1. /profile?tab=orders. 2. Mở /order/{id}. | K70: Thấy đơn và dòng thời gian trạng thái. | L70: Giao diện. | N70: Chưa test
A71: PH3-11 | B71: PH3 – Giỏ hàng & đơn hàng | C71: Bảo hành | D71: Tab bảo hành | E71: Chức năng | F71: Thấp | G71: customer | H71: Đơn DELIVERED, sản phẩm có bảo hành > 0. | I71: 1. /profile?tab=warranty. | K71: Có sản phẩm vừa nhận cùng hạn bảo hành. | L71: Giao diện. | N71: Chưa test
A72: PH3-12 | B72: PH3 – Giỏ hàng & đơn hàng | C72: Hủy đơn | D72: Khách hủy đơn đã xác nhận | E72: Chức năng | F72: Cao | G72: customer | H72: Đơn COD CONFIRMED, đặt < 2 giờ. | I72: 1. Mở đơn → Hủy đơn → xác nhận. | K72: Đơn CANCELLED; tồn kho được trả lại. | L72: Lịch sử kho có dòng RELEASE. | N72: Chưa test
A73: PH3-13 | B73: PH3 – Giỏ hàng & đơn hàng | C73: Hủy đơn | D73: Khách hủy đơn đang chờ thanh toán | E73: Chức năng | F73: Trung bình | G73: customer | H73: Đơn VNPay ở AWAITING_PAYMENT. | I73: 1. Mở đơn → Hủy đơn. | K73: Đơn CANCELLED; tồn kho được trả lại. | L73: DB và lịch sử kho. | N73: Chưa test
A74: PH3-14 | B74: PH3 – Giỏ hàng & đơn hàng | C74: Hủy đơn | D74: Đơn đang giao không cho khách hủy | E74: Phân quyền | F74: Cao | G74: customer, admin | H74: Đơn SHIPPED. | I74: 1. Khách mở đơn. 2. Admin mở đơn. | K74: Khách không thấy nút hủy; admin có nút Hủy Giao Hàng. | L74: Giao diện 2 phía. | N74: Chưa test
A75: PH3-15 | B75: PH3 – Giỏ hàng & đơn hàng | C75: Hủy đơn | D75: Trạng thái cuối không đổi được | E75: Ngoại lệ | F75: Trung bình | G75: admin | H75: Đơn DELIVERED hoặc CANCELLED. | I75: 1. Thử đổi trạng thái đơn. | K75: Không có thao tác đổi trạng thái / bị từ chối. | L75: Giao diện. | N75: Chưa test
A76: PH3-16 | B76: PH3 – Giỏ hàng & đơn hàng | C76: Hủy đơn | D76: Quá 2 giờ thì khách hết nút hủy | E76: Ngoại lệ | F76: Thấp | G76: customer | H76: Đơn CONFIRMED đặt > 2 giờ. | I76: 1. Mở chi tiết đơn. | K76: Nút hủy không còn hiển thị. | L76: Giao diện. Lưu ý: giới hạn 2 giờ chỉ có ở FE. | N76: Chưa test
A77: PH3-17 | B77: PH3 – Giỏ hàng & đơn hàng | C77: Đặt hàng | D77: Đặt số lượng vượt tồn kho ở checkout | E77: Ngoại lệ | F77: Cao | G77: customer | I77: 1. Đặt hàng với số lượng > tồn kho. | K77: Bị từ chối, báo không đủ hàng (HTTP 400). | L77: F12 → Network. | N77: Chưa test
A78: PH3-18 | B78: PH3 – Giỏ hàng & đơn hàng | C78: Đặt hàng | D78: Bấm đặt hàng 2 lần liên tiếp | E78: Ngoại lệ | F78: Cao | G78: customer | I78: 1. Bấm đặt hàng 2 lần thật nhanh. | K78: Chỉ tạo 1 đơn (Idempotency-Key). | L78: Danh sách đơn; bảng orders. | N78: Chưa test
A79: PH3-19 | B79: PH3 – Giỏ hàng & đơn hàng | C79: Đơn bỏ dở | D79: Tự hủy đơn chờ thanh toán quá 30 phút | E79: Chức năng | F79: Trung bình | G79: customer | H79: Đơn VNPay ở AWAITING_PAYMENT. | I79: 1. Không thanh toán, chờ > 30 phút. | K79: Đơn tự CANCELLED, tồn kho được trả lại. | L79: DB và lịch sử kho. | N79: Chưa test
A80: PH3-20 | B80: PH3 – Giỏ hàng & đơn hàng | C80: Checkout | D80: Checkout khi giỏ trống | E80: Ngoại lệ | F80: Trung bình | G80: customer | H80: Giỏ trống. | I80: 1. Mở /checkout. | K80: Không cho đặt hàng, báo giỏ trống. | L80: Giao diện. | N80: Chưa test
A81: PH3-21 | B81: PH3 – Giỏ hàng & đơn hàng | C81: Checkout | D81: Checkout thiếu địa chỉ hoặc SĐT | E81: Ngoại lệ | F81: Trung bình | G81: customer | I81: 1. Bỏ trống địa chỉ/SĐT, bấm đặt hàng. | K81: Báo lỗi bắt buộc nhập. | L81: Giao diện. | N81: Chưa test
A82: PH3-22 | B82: PH3 – Giỏ hàng & đơn hàng | C82: Đặt hàng | D82: Hai khách cùng mua món cuối cùng | E82: Ngoại lệ | F82: Thấp | G82: 2 tài khoản customer | H82: Phiên bản còn đúng 1 sản phẩm. | I82: 1. Hai trình duyệt cùng thêm vào giỏ. 2. Bấm đặt hàng gần như cùng lúc. | K82: Chỉ 1 đơn thành công; người còn lại báo hết hàng. | L82: Bảng orders; tồn kho không âm. | N82: Chưa test
A83: PH4-01 | B83: PH4 – Tồn kho | C83: Tồn kho | D83: Danh sách sắp hết hàng | E83: Chức năng | F83: Trung bình | G83: admin | I83: 1. Quản Lý Tồn Kho → xem danh sách sắp hết. | K83: Hiện các phiên bản có tồn ≤ ngưỡng (mặc định 10). | L83: Giao diện. | N83: Chưa test
A84: PH4-02 | B84: PH4 – Tồn kho | C84: Nhập kho | D84: Nhập thêm hàng | E84: Chức năng | F84: Cao | G84: admin | I84: 1. Chọn một phiên bản → Nhập thêm hàng. | J84: Số lượng 5 | K84: Tồn kho tăng 5; trang sản phẩm khách thấy còn hàng. | L84: Lịch sử kho có dòng RESTOCK. | N84: Chưa test
A85: PH4-03 | B85: PH4 – Tồn kho | C85: Nhập kho | D85: Nhập số lượng 0 hoặc âm | E85: Ngoại lệ | F85: Trung bình | G85: admin | I85: 1. Nhập kho với số lượng 0, rồi −5. | J85: 0, −5 | K85: Bị từ chối, báo lỗi số lượng. | L85: Giao diện / F12 → Network. | N85: Chưa test
A86: PH4-04 | B86: PH4 – Tồn kho | C86: Nhập kho | D86: Staff nhập kho | E86: Phân quyền | F86: Thấp | G86: staff | I86: 1. Nhập thêm hàng cho một phiên bản. | K86: Thành công. | L86: Lịch sử kho. | N86: Chưa test
A87: PH4-05 | B87: PH4 – Tồn kho | C87: Lịch sử | D87: Lịch sử giao dịch kho | E87: Chức năng | F87: Trung bình | G87: admin | H87: Đã chạy PH3, PH4-02. | I87: 1. Xem lịch sử giao dịch của sản phẩm. | K87: Có các dòng DEDUCT, RELEASE, RESTOCK đúng thứ tự thời gian. | L87: Giao diện. | N87: Chưa test
A88: PH4-06 | B88: PH4 – Tồn kho | C88: Đồng bộ | D88: Đồng bộ tồn kho sang Redis | E88: Tích hợp | F88: Trung bình | G88: admin | I88: 1. Bấm Đồng bộ Redis. 2. Chạy `docker exec infra-redis redis-cli GET product:stock:{pid}:{vid}`. | K88: Số trong Redis khớp số trong DB. | L88: So sánh redis-cli với giao diện tồn kho. | N88: Chưa test
A89: PH5-01 | B89: PH5 – Thanh toán | C89: VNPay | D89: Chuyển sang cổng VNPay | E89: Tích hợp | F89: Cao | G89: customer | I89: 1. /checkout chọn VNPay → đặt hàng. | K89: Chuyển sang sandbox.vnpayment.vn. | L89: URL trình duyệt. | N89: Chưa test
A90: PH5-02 | B90: PH5 – Thanh toán | C90: VNPay | D90: Thanh toán VNPay thành công | E90: Tích hợp | F90: Cao | G90: customer | H90: PH5-01. | I90: 1. Chọn ngân hàng NCB, nhập thẻ test, OTP. | J90: NCB · 9704198526191432198 · NGUYEN VAN A · 07/15 · OTP 123456 | K90: Quay về /order/{id}?paymentStatus=00, đơn CONFIRMED. | L90: DB orders; tab Transaction. | N90: Chưa test
A91: PH5-03 | B91: PH5 – Thanh toán | C91: VNPay | D91: Hủy giao dịch trên VNPay | E91: Ngoại lệ | F91: Cao | G91: customer | I91: 1. Đặt đơn VNPay. 2. Trên trang VNPay bấm Hủy giao dịch. | K91: Đơn CANCELLED, tồn kho được trả lại. | L91: DB và lịch sử kho. | N91: Chưa test
A92: PH5-04 | B92: PH5 – Thanh toán | C92: VNPay | D92: Không thanh toán trong 15 phút | E92: Ngoại lệ | F92: Trung bình | G92: customer | I92: 1. Đặt đơn VNPay, không thanh toán. 2. Chờ > 15 phút. | K92: Giao dịch hết hạn (EXPIRED); đơn bị hủy theo job dọn đơn. | L92: Tab Transaction; DB. | N92: Chưa test
A93: PH5-05 | B93: PH5 – Thanh toán | C93: VNPay | D93: Callback VNPay bị sửa tham số | E93: Bảo mật | F93: Cao | G93: customer | H93: Có URL callback từ PH5-02. | I93: 1. Sửa giá trị `vnp_Amount` trong URL callback rồi gửi lại. | K93: Không xác nhận đơn; chữ ký bị đánh giá là không hợp lệ. | L93: Bảng webhook_logs: signature_valid = false. | N93: Chưa test
A94: PH5-06 | B94: PH5 – Thanh toán | C94: Quản trị | D94: Xem danh sách giao dịch | E94: Chức năng | F94: Trung bình | G94: admin | I94: 1. Tab Transaction. | K94: Thấy các giao dịch COD/VNPay và trạng thái. | L94: Giao diện. | N94: Chưa test
A95: PH5-07 | B95: PH5 – Thanh toán | C95: Hoàn tiền | D95: Admin hoàn tiền toàn phần | E95: Chức năng | F95: Cao | G95: admin | H95: Có giao dịch VNPay SUCCESS. | I95: 1. Chọn giao dịch → hoàn tiền toàn bộ. | K95: Tạo bản ghi hoàn tiền; giao dịch chuyển REFUNDED (hoặc PENDING_MANUAL nếu sandbox từ chối). | L95: Tab Transaction; bảng refunds. | N95: Chưa test
A96: PH5-08 | B96: PH5 – Thanh toán | C96: Hoàn tiền | D96: Admin hoàn tiền một phần | E96: Chức năng | F96: Trung bình | G96: admin | H96: Có giao dịch VNPay SUCCESS. | I96: 1. Hoàn một phần số tiền. | J96: 50% số tiền | K96: Giao dịch chuyển PARTIALLY_REFUNDED. | L96: Tab Transaction. | N96: Chưa test
A97: PH5-09 | B97: PH5 – Thanh toán | C97: Hoàn tiền | D97: Staff không được hoàn tiền | E97: Phân quyền | F97: Cao | G97: staff | I97: 1. Thử hoàn tiền một giao dịch. | K97: Bị từ chối (HTTP 403). | L97: F12 → Network. | N97: Chưa test
A98: PH5-10 | B98: PH5 – Thanh toán | C98: Hoàn tiền | D98: Tự hoàn tiền khi hủy đơn đã trả VNPay | E98: Tích hợp | F98: Cao | G98: customer | H98: Đơn VNPay CONFIRMED. | I98: 1. Khách hủy đơn. 2. Chờ 1–2 phút. | K98: Giao dịch chuyển REFUND_PENDING rồi REFUNDED (hoặc PENDING_MANUAL). | L98: Tab Transaction; bảng refunds. | N98: Chưa test
A99: PH5-11 | B99: PH5 – Thanh toán | C99: COD | D99: COD chỉ thành công khi đã giao | E99: Chức năng | F99: Trung bình | G99: admin | H99: Đơn COD CONFIRMED. | I99: 1. Xem giao dịch COD trước và sau khi đơn DELIVERED. | K99: Trước khi giao: chưa SUCCESS; sau khi DELIVERED: SUCCESS. | L99: Tab Transaction. | N99: Chưa test
A100: PH6-01 | B100: PH6 – Khuyến mãi & chiến dịch | C100: Trình dựng chiến dịch | D100: Mở trình dựng chiến dịch | E100: Chức năng | F100: Cao | G100: admin | I100: 1. Tab Coupon Code → tạo mới. | K100: Canvas kéo thả hiện ra. | L100: Giao diện. | N100: Chưa test
...

Sheet Tổng hợp
A1: TỔNG HỢP KẾT QUẢ TEST
A2: Tự cập nhật theo cột Trạng thái ở sheet 'Test case'. Tỷ lệ đạt = Đạt / (Đạt + Không đạt + Bị chặn).
A4: Phân hệ | B4: Tổng | C4: Đạt | D4: Không đạt | E4: Bị chặn | F4: Bỏ qua | G4: Chưa test | H4: % đã test | I4: % đạt
A5: SYS – Hạ tầng & khởi động | B5: =COUNTIFS('Test case'!$B$2:$B$187,$A5) -> 9 | C5: =COUNTIFS('Test case'!$B$2:$B$187,$A5,'Test case'!$N$2:$N$187,"Đạt") -> 0 | D5: =COUNTIFS('Test case'!$B$2:$B$187,$A5,'Test case'!$N$2:$N$187,"Không đạt") -> 0 | E5: =COUNTIFS('Test case'!$B$2:$B$187,$A5,'Test case'!$N$2:$N$187,"Bị chặn") -> 0 | F5: =COUNTIFS('Test case'!$B$2:$B$187,$A5,'Test case'!$N$2:$N$187,"Bỏ qua") -> 0 | G5: =COUNTIFS('Test case'!$B$2:$B$187,$A5,'Test case'!$N$2:$N$187,"Chưa test") -> 9 | H5: =IFERROR((B5-G5)/B5,0) -> 0 | I5: =IFERROR(C5/(C5+D5+E5),0) -> 0
A6: PH1 – Tài khoản & phân quyền | B6: =COUNTIFS('Test case'!$B$2:$B$187,$A6) -> 19 | C6: =COUNTIFS('Test case'!$B$2:$B$187,$A6,'Test case'!$N$2:$N$187,"Đạt") -> 0 | D6: =COUNTIFS('Test case'!$B$2:$B$187,$A6,'Test case'!$N$2:$N$187,"Không đạt") -> 0 | E6: =COUNTIFS('Test case'!$B$2:$B$187,$A6,'Test case'!$N$2:$N$187,"Bị chặn") -> 0 | F6: =COUNTIFS('Test case'!$B$2:$B$187,$A6,'Test case'!$N$2:$N$187,"Bỏ qua") -> 0 | G6: =COUNTIFS('Test case'!$B$2:$B$187,$A6,'Test case'!$N$2:$N$187,"Chưa test") -> 19 | H6: =IFERROR((B6-G6)/B6,0) -> 0 | I6: =IFERROR(C6/(C6+D6+E6),0) -> 0
A7: PH2 – Sản phẩm & tìm kiếm | B7: =COUNTIFS('Test case'!$B$2:$B$187,$A7) -> 31 | C7: =COUNTIFS('Test case'!$B$2:$B$187,$A7,'Test case'!$N$2:$N$187,"Đạt") -> 0 | D7: =COUNTIFS('Test case'!$B$2:$B$187,$A7,'Test case'!$N$2:$N$187,"Không đạt") -> 0 | E7: =COUNTIFS('Test case'!$B$2:$B$187,$A7,'Test case'!$N$2:$N$187,"Bị chặn") -> 0 | F7: =COUNTIFS('Test case'!$B$2:$B$187,$A7,'Test case'!$N$2:$N$187,"Bỏ qua") -> 0 | G7: =COUNTIFS('Test case'!$B$2:$B$187,$A7,'Test case'!$N$2:$N$187,"Chưa test") -> 31 | H7: =IFERROR((B7-G7)/B7,0) -> 0 | I7: =IFERROR(C7/(C7+D7+E7),0) -> 0
A8: PH3 – Giỏ hàng & đơn hàng | B8: =COUNTIFS('Test case'!$B$2:$B$187,$A8) -> 22 | C8: =COUNTIFS('Test case'!$B$2:$B$187,$A8,'Test case'!$N$2:$N$187,"Đạt") -> 0 | D8: =COUNTIFS('Test case'!$B$2:$B$187,$A8,'Test case'!$N$2:$N$187,"Không đạt") -> 0 | E8: =COUNTIFS('Test case'!$B$2:$B$187,$A8,'Test case'!$N$2:$N$187,"Bị chặn") -> 0 | F8: =COUNTIFS('Test case'!$B$2:$B$187,$A8,'Test case'!$N$2:$N$187,"Bỏ qua") -> 0 | G8: =COUNTIFS('Test case'!$B$2:$B$187,$A8,'Test case'!$N$2:$N$187,"Chưa test") -> 22 | H8: =IFERROR((B8-G8)/B8,0) -> 0 | I8: =IFERROR(C8/(C8+D8+E8),0) -> 0
A9: PH4 – Tồn kho | B9: =COUNTIFS('Test case'!$B$2:$B$187,$A9) -> 6 | C9: =COUNTIFS('Test case'!$B$2:$B$187,$A9,'Test case'!$N$2:$N$187,"Đạt") -> 0 | D9: =COUNTIFS('Test case'!$B$2:$B$187,$A9,'Test case'!$N$2:$N$187,"Không đạt") -> 0 | E9: =COUNTIFS('Test case'!$B$2:$B$187,$A9,'Test case'!$N$2:$N$187,"Bị chặn") -> 0 | F9: =COUNTIFS('Test case'!$B$2:$B$187,$A9,'Test case'!$N$2:$N$187,"Bỏ qua") -> 0 | G9: =COUNTIFS('Test case'!$B$2:$B$187,$A9,'Test case'!$N$2:$N$187,"Chưa test") -> 6 | H9: =IFERROR((B9-G9)/B9,0) -> 0 | I9: =IFERROR(C9/(C9+D9+E9),0) -> 0
A10: PH5 – Thanh toán | B10: =COUNTIFS('Test case'!$B$2:$B$187,$A10) -> 11 | C10: =COUNTIFS('Test case'!$B$2:$B$187,$A10,'Test case'!$N$2:$N$187,"Đạt") -> 0 | D10: =COUNTIFS('Test case'!$B$2:$B$187,$A10,'Test case'!$N$2:$N$187,"Không đạt") -> 0 | E10: =COUNTIFS('Test case'!$B$2:$B$187,$A10,'Test case'!$N$2:$N$187,"Bị chặn") -> 0 | F10: =COUNTIFS('Test case'!$B$2:$B$187,$A10,'Test case'!$N$2:$N$187,"Bỏ qua") -> 0 | G10: =COUNTIFS('Test case'!$B$2:$B$187,$A10,'Test case'!$N$2:$N$187,"Chưa test") -> 11 | H10: =IFERROR((B10-G10)/B10,0) -> 0 | I10: =IFERROR(C10/(C10+D10+E10),0) -> 0
A11: PH6 – Khuyến mãi & chiến dịch | B11: =COUNTIFS('Test case'!$B$2:$B$187,$A11) -> 24 | C11: =COUNTIFS('Test case'!$B$2:$B$187,$A11,'Test case'!$N$2:$N$187,"Đạt") -> 0 | D11: =COUNTIFS('Test case'!$B$2:$B$187,$A11,'Test case'!$N$2:$N$187,"Không đạt") -> 0 | E11: =COUNTIFS('Test case'!$B$2:$B$187,$A11,'Test case'!$N$2:$N$187,"Bị chặn") -> 0 | F11: =COUNTIFS('Test case'!$B$2:$B$187,$A11,'Test case'!$N$2:$N$187,"Bỏ qua") -> 0 | G11: =COUNTIFS('Test case'!$B$2:$B$187,$A11,'Test case'!$N$2:$N$187,"Chưa test") -> 24 | H11: =IFERROR((B11-G11)/B11,0) -> 0 | I11: =IFERROR(C11/(C11+D11+E11),0) -> 0
A12: PH7 – Thông báo email | B12: =COUNTIFS('Test case'!$B$2:$B$187,$A12) -> 6 | C12: =COUNTIFS('Test case'!$B$2:$B$187,$A12,'Test case'!$N$2:$N$187,"Đạt") -> 0 | D12: =COUNTIFS('Test case'!$B$2:$B$187,$A12,'Test case'!$N$2:$N$187,"Không đạt") -> 0 | E12: =COUNTIFS('Test case'!$B$2:$B$187,$A12,'Test case'!$N$2:$N$187,"Bị chặn") -> 0 | F12: =COUNTIFS('Test case'!$B$2:$B$187,$A12,'Test case'!$N$2:$N$187,"Bỏ qua") -> 0 | G12: =COUNTIFS('Test case'!$B$2:$B$187,$A12,'Test case'!$N$2:$N$187,"Chưa test") -> 6 | H12: =IFERROR((B12-G12)/B12,0) -> 0 | I12: =IFERROR(C12/(C12+D12+E12),0) -> 0
A13: PH8 – Hành vi & gợi ý | B13: =COUNTIFS('Test case'!$B$2:$B$187,$A13) -> 13 | C13: =COUNTIFS('Test case'!$B$2:$B$187,$A13,'Test case'!$N$2:$N$187,"Đạt") -> 0 | D13: =COUNTIFS('Test case'!$B$2:$B$187,$A13,'Test case'!$N$2:$N$187,"Không đạt") -> 0 | E13: =COUNTIFS('Test case'!$B$2:$B$187,$A13,'Test case'!$N$2:$N$187,"Bị chặn") -> 0 | F13: =COUNTIFS('Test case'!$B$2:$B$187,$A13,'Test case'!$N$2:$N$187,"Bỏ qua") -> 0 | G13: =COUNTIFS('Test case'!$B$2:$B$187,$A13,'Test case'!$N$2:$N$187,"Chưa test") -> 13 | H13: =IFERROR((B13-G13)/B13,0) -> 0 | I13: =IFERROR(C13/(C13+D13+E13),0) -> 0
A14: PH9 – Phân tích AI & churn | B14: =COUNTIFS('Test case'!$B$2:$B$187,$A14) -> 9 | C14: =COUNTIFS('Test case'!$B$2:$B$187,$A14,'Test case'!$N$2:$N$187,"Đạt") -> 0 | D14: =COUNTIFS('Test case'!$B$2:$B$187,$A14,'Test case'!$N$2:$N$187,"Không đạt") -> 0 | E14: =COUNTIFS('Test case'!$B$2:$B$187,$A14,'Test case'!$N$2:$N$187,"Bị chặn") -> 0 | F14: =COUNTIFS('Test case'!$B$2:$B$187,$A14,'Test case'!$N$2:$N$187,"Bỏ qua") -> 0 | G14: =COUNTIFS('Test case'!$B$2:$B$187,$A14,'Test case'!$N$2:$N$187,"Chưa test") -> 9 | H14: =IFERROR((B14-G14)/B14,0) -> 0 | I14: =IFERROR(C14/(C14+D14+E14),0) -> 0
A15: PH10 – Chatbot & hỗ trợ | B15: =COUNTIFS('Test case'!$B$2:$B$187,$A15) -> 15 | C15: =COUNTIFS('Test case'!$B$2:$B$187,$A15,'Test case'!$N$2:$N$187,"Đạt") -> 0 | D15: =COUNTIFS('Test case'!$B$2:$B$187,$A15,'Test case'!$N$2:$N$187,"Không đạt") -> 0 | E15: =COUNTIFS('Test case'!$B$2:$B$187,$A15,'Test case'!$N$2:$N$187,"Bị chặn") -> 0 | F15: =COUNTIFS('Test case'!$B$2:$B$187,$A15,'Test case'!$N$2:$N$187,"Bỏ qua") -> 0 | G15: =COUNTIFS('Test case'!$B$2:$B$187,$A15,'Test case'!$N$2:$N$187,"Chưa test") -> 15 | H15: =IFERROR((B15-G15)/B15,0) -> 0 | I15: =IFERROR(C15/(C15+D15+E15),0) -> 0
A16: SEC – Bảo mật | B16: =COUNTIFS('Test case'!$B$2:$B$187,$A16) -> 12 | C16: =COUNTIFS('Test case'!$B$2:$B$187,$A16,'Test case'!$N$2:$N$187,"Đạt") -> 0 | D16: =COUNTIFS('Test case'!$B$2:$B$187,$A16,'Test case'!$N$2:$N$187,"Không đạt") -> 0 | E16: =COUNTIFS('Test case'!$B$2:$B$187,$A16,'Test case'!$N$2:$N$187,"Bị chặn") -> 0 | F16: =COUNTIFS('Test case'!$B$2:$B$187,$A16,'Test case'!$N$2:$N$187,"Bỏ qua") -> 0 | G16: =COUNTIFS('Test case'!$B$2:$B$187,$A16,'Test case'!$N$2:$N$187,"Chưa test") -> 12 | H16: =IFERROR((B16-G16)/B16,0) -> 0 | I16: =IFERROR(C16/(C16+D16+E16),0) -> 0
... A18: E2E – Luồng xuyên suốt | B18: =COUNTIFS('Test case'!$B$2:$B$187,$A18) -> 3 | C18: =COUNTIFS('Test case'!$B$2:$B$187,$A18,'Test case'!$N$2:$N$187,"Đạt") -> 0 | D18: =COUNTIFS('Test case'!$B$2:$B$187,$A18,'Test case'!$N$2:$N$187,"Không đạt") -> 0 | E18: =COUNTIFS('Test case'!$B$2:$B$187,$A18,'Test case'!$N$2:$N$187,"Bị chặn") -> 0 | F18: =COUNTIFS('Test case'!$B$2:$B$187,$A18,'Test case'!$N$2:$N$187,"Bỏ qua") -> 0 | G18: =COUNTIFS('Test case'!$B$2:$B$187,$A18,'Test case'!$N$2:$N$187,"Chưa test") -> 3 | H18: =IFERROR((B18-G18)/B18,0) -> 0 | I18: =IFERROR(C18/(C18+D18+E18),0) -> 0
A19: TỔNG CỘNG | B19: =SUM(B5:B18) -> 186 | C19: =SUM(C5:C18) -> 0 | D19: =SUM(D5:D18) -> 0 | E19: =SUM(E5:E18) -> 0 | F19: =SUM(F5:F18) -> 0 | G19: =SUM(G5:G18) -> 186 | H19: =IFERROR((B19-G19)/B19,0) -> 0 | I19: =IFERROR(C19/(C19+D19+E19),0) -> 0
A20: Kiểm tra | B20: =IF(B19=COUNTA('Test case'!$A$2:$A$187),"Khớp tổng số test case","Lệch: kiểm tra cột Phân hệ") -> Khớp tổng số test case
A22: Theo mức ưu tiên
A23: Ưu tiên | B23: Tổng | C23: Đạt | D23: Không đạt | E23: Bị chặn | F23: Bỏ qua | G23: Chưa test
A24: Cao | B24: =COUNTIFS('Test case'!$F$2:$F$187,$A24) -> 70 | C24: =COUNTIFS('Test case'!$F$2:$F$187,$A24,'Test case'!$N$2:$N$187,"Đạt") -> 0 | D24: =COUNTIFS('Test case'!$F$2:$F$187,$A24,'Test case'!$N$2:$N$187,"Không đạt") -> 0 | E24: =COUNTIFS('Test case'!$F$2:$F$187,$A24,'Test case'!$N$2:$N$187,"Bị chặn") -> 0 | F24: =COUNTIFS('Test case'!$F$2:$F$187,$A24,'Test case'!$N$2:$N$187,"Bỏ qua") -> 0 | G24: =COUNTIFS('Test case'!$F$2:$F$187,$A24,'Test case'!$N$2:$N$187,"Chưa test") -> 70
A25: Trung bình | B25: =COUNTIFS('Test case'!$F$2:$F$187,$A25) -> 75 | C25: =COUNTIFS('Test case'!$F$2:$F$187,$A25,'Test case'!$N$2:$N$187,"Đạt") -> 0 | D25: =COUNTIFS('Test case'!$F$2:$F$187,$A25,'Test case'!$N$2:$N$187,"Không đạt") -> 0 | E25: =COUNTIFS('Test case'!$F$2:$F$187,$A25,'Test case'!$N$2:$N$187,"Bị chặn") -> 0 | F25: =COUNTIFS('Test case'!$F$2:$F$187,$A25,'Test case'!$N$2:$N$187,"Bỏ qua") -> 0 | G25: =COUNTIFS('Test case'!$F$2:$F$187,$A25,'Test case'!$N$2:$N$187,"Chưa test") -> 75
A26: Thấp | B26: =COUNTIFS('Test case'!$F$2:$F$187,$A26) -> 41 | C26: =COUNTIFS('Test case'!$F$2:$F$187,$A26,'Test case'!$N$2:$N$187,"Đạt") -> 0 | D26: =COUNTIFS('Test case'!$F$2:$F$187,$A26,'Test case'!$N$2:$N$187,"Không đạt") -> 0 | E26: =COUNTIFS('Test case'!$F$2:$F$187,$A26,'Test case'!$N$2:$N$187,"Bị chặn") -> 0 | F26: =COUNTIFS('Test case'!$F$2:$F$187,$A26,'Test case'!$N$2:$N$187,"Bỏ qua") -> 0 | G26: =COUNTIFS('Test case'!$F$2:$F$187,$A26,'Test case'!$N$2:$N$187,"Chưa test") -> 41

Sheet Hành vi đã biết
A1: HÀNH VI ĐÃ BIẾT – KHÔNG GHI LÀ LỖI MỚI
A2: Nguồn: docs/test/HUONG_DAN_TEST_THU_CONG.md §13 và rà soát code nhánh develop (10/2026).
A4: Chức năng | B4: Hành vi hiện tại
A5: Tìm kiếm trên web | B5: Ô tìm kiếm gọi product-service (Elasticsearch, so khớp chứa chuỗi), chưa dùng tìm kiếm ngữ nghĩa; tìm kiếm ngữ nghĩa chỉ thử được qua Swagger 8001.
A6: Tìm kiếm bằng ảnh | B6: Nhãn 'YOLO v8 detected' luôn hiện; 'Độ khớp %' không phản ánh độ tin cậy; tiêu đề hiện Kết quả cho "".
A7: Sản phẩm liên quan | B7: Luôn là 8 sản phẩm đầu danh sách, không phải AI.
A8: Điểm đánh giá | B8: Trang sản phẩm hiện 0 sao dù có đánh giá.
A9: /stores, /tradein | B9: Chưa có backend.
A10: Vận chuyển | B10: Mã vận đơn giả MOCK-GHTK-*, phí cố định 30.000đ.
A11: Hủy đơn | B11: Giới hạn 2 giờ chỉ kiểm tra ở FE; API không kiểm tra thời gian. Không có chọn lý do hủy.
A12: Điểm thưởng | B12: Không tự cộng cho mọi đơn, chỉ cộng qua chiến dịch.
A13: Chiến dịch hẹn giờ | B13: Hành động cần người dùng bị bỏ qua; xóa chiến dịch không gỡ deployment Camunda.
A14: Thông báo | B14: Không có thông báo đẩy (FCM chỉ lưu token); chuông thông báo admin chỉ trang trí; chưa có email hoàn tiền.
A15: Gợi ý mua kèm (giỏ hàng) | B15: Trả danh sách phổ biến, chưa dựa vào sản phẩm trong giỏ.
... A20: Kiểm tra chiến dịch không hợp lệ | B20: API trả HTTP 200 với code VALIDATION_FAILED, không phải 400.

Sheet Ghi lỗi
A1: Mã lỗi | B1: Test case ID | C1: Phân hệ | D1: Mức độ | E1: Tiêu đề lỗi | F1: Bước tái hiện | G1: Kết quả mong đợi | H1: Kết quả thực tế | I1: Ảnh / log | J1: Người test | K1: Ngày phát hiện | L1: Trạng thái xử lý
A2: BUG-VD | B2: PH3-17 | C2: PH3 – Giỏ hàng & đơn hàng | D2: Cao | E2: (VÍ DỤ – xóa dòng này khi dùng) Đặt vượt tồn kho vẫn tạo đơn | F2: 1. Đăng nhập customer. 2. Đặt 15 sản phẩm khi tồn kho 10. | G2: Bị từ chối, HTTP 400 | H2: Đơn được tạo ở PENDING | I2: screenshot-01.png | J2: Tên bạn | K2: 17/10/2026 | L2: Mới
